{"v":"5.10.2","fr":29.9700012207031,"ip":0,"op":181.000007372281,"w":500,"h":500,"nm":"Sun","ddd":0,"assets":[],"layers":[{"ddd":0,"ind":1,"ty":1,"nm":"Black Solid 2","sr":1,"ks":{"o":{"a":0,"k":100,"ix":11},"r":{"a":1,"k":[{"i":{"x":[0.833],"y":[0.833]},"o":{"x":[0.167],"y":[0.167]},"t":30,"s":[0]},{"t":180.00000733155,"s":[360]}],"ix":10,"x":"var $bm_rt;\nfunction easeandwizz_inoutQuad(t, b, c, d) {\n    if ((t /= d / 2) < 1)\n        return $bm_sum($bm_mul($bm_mul($bm_div(c, 2), t), t), b);\n    return $bm_sum($bm_mul($bm_div($bm_neg(c), 2), $bm_sub($bm_mul(--t, $bm_sub(t, 2)), 1)), b);\n}\nfunction easeAndWizz() {\n    var t, d, sX, eX;\n    var n = 0;\n    if (numKeys > 0) {\n        n = nearestKey(time).index;\n        if (key(n).time > time) {\n            n--;\n        }\n    }\n    try {\n        var key1 = key(n);\n        var key2 = key($bm_sum(n, 1));\n    } catch (e) {\n        return null;\n    }\n    t = $bm_sub(time, key1.time);\n    d = $bm_sub(key2.time, key1.time);\n    sX = key1.time;\n    eX = $bm_sub(key2.time, key1.time);\n    if (time < key1.time || time > key2.time) {\n        return null;\n    } else {\n        return valueAtTime(easeandwizz_inoutQuad(t, sX, eX, d));\n    }\n}\n$bm_rt = easeAndWizz() || value;"},"p":{"a":0,"k":[250,250,0],"ix":2,"l":2},"a":{"a":0,"k":[250,250,0],"ix":1,"l":2},"s":{"a":0,"k":[100,100,100],"ix":6,"l":2}},"ao":0,"hasMask":true,"masksProperties":[{"inv":false,"mode":"f","pt":{"a":0,"k":{"i":[[0,0],[-1.907,0.169],[0,0],[8.42,-1.675]],"o":[[1.846,-0.359],[0,0],[-8.548,0.8],[0,0]],"v":[[239.209,195.931],[244.841,195.135],[226.687,1.225],[201.219,4.939]],"c":true},"ix":1},"o":{"a":0,"k":100,"ix":3},"x":{"a":0,"k":0,"ix":4},"nm":"Mask 1"},{"inv":false,"mode":"f","pt":{"a":0,"k":{"i":[[0,0],[1.895,-0.183],[0,0],[-8.42,1.675]],"o":[[-1.835,0.37],[0,0],[8.547,-0.8],[0,0]],"v":[[260.711,304.035],[255.113,304.868],[273.29,499.026],[298.759,495.309]],"c":true},"ix":1},"o":{"a":0,"k":100,"ix":3},"x":{"a":0,"k":0,"ix":4},"nm":"Mask 2"},{"inv":false,"mode":"f","pt":{"a":0,"k":{"i":[[0,0],[0.07,0],[1.791,0.178],[0,0],[-8.585,0]],"o":[[-0.071,0],[-1.838,0],[0,0],[8.54,0.882],[0,0]],"v":[[249.988,305.123],[249.777,305.123],[244.331,304.855],[224.284,498.789],[249.988,500.114]],"c":true},"ix":1},"o":{"a":0,"k":100,"ix":3},"x":{"a":0,"k":0,"ix":4},"nm":"Mask 3"},{"inv":false,"mode":"f","pt":{"a":0,"k":{"i":[[1.797,0.545],[0,0],[-8.42,-1.675],[0,0]],"o":[[0,0],[8.203,2.532],[0,0],[-1.869,-0.362]],"v":[[233.747,302.75],[176.266,488.997],[201.218,495.312],[239.249,304.115]],"c":true},"ix":1},"o":{"a":0,"k":100,"ix":3},"x":{"a":0,"k":0,"ix":4},"nm":"Mask 4"},{"inv":false,"mode":"f","pt":{"a":0,"k":{"i":[[0,0],[1.66,0.893],[0,0],[-7.932,-3.285]],"o":[[-1.757,-0.72],[0,0],[7.552,4.082],[0,0]],"v":[[228.906,301.023],[223.777,298.601],[131.082,470.025],[154.322,481.085]],"c":true},"ix":1},"o":{"a":0,"k":100,"ix":3},"x":{"a":0,"k":0,"ix":4},"nm":"Mask 5"},{"inv":false,"mode":"f","pt":{"a":0,"k":{"i":[[1.458,1.203],[0,0],[-7.138,-4.77],[0,0]],"o":[[0,0],[6.61,5.477],[0,0],[-1.579,-1.05]],"v":[[214.807,292.576],[90.466,442.602],[111.102,457.983],[219.365,295.956]],"c":true},"ix":1},"o":{"a":0,"k":100,"ix":3},"x":{"a":0,"k":0,"ix":4},"nm":"Mask 6"},{"inv":false,"mode":"f","pt":{"a":0,"k":{"i":[[1.199,1.467],[0,0],[-6.07,-6.072],[0,0]],"o":[[0,0],[5.414,6.665],[0,0],[-1.342,-1.334]],"v":[[207.178,284.914],[55.98,407.781],[73.219,426.895],[210.993,289.118]],"c":true},"ix":1},"o":{"a":0,"k":100,"ix":3},"x":{"a":0,"k":0,"ix":4},"nm":"Mask 7"},{"inv":false,"mode":"f","pt":{"a":0,"k":{"i":[[0.892,1.677],[0,0],[-4.77,-7.137],[0,0]],"o":[[0,0],[4.01,7.592],[0,0],[-1.055,-1.57]],"v":[[201.185,275.909],[28.951,366.902],[42.13,389.011],[204.109,280.781]],"c":true},"ix":1},"o":{"a":0,"k":100,"ix":3},"x":{"a":0,"k":0,"ix":4},"nm":"Mask 8"},{"inv":false,"mode":"f","pt":{"a":0,"k":{"i":[[0.546,1.827],[0,0],[-3.285,-7.93],[0,0]],"o":[[0,0],[2.452,8.227],[0,0],[-0.725,-1.742]],"v":[[197.075,265.897],[10.416,321.537],[19.028,345.791],[198.984,271.251]],"c":true},"ix":1},"o":{"a":0,"k":100,"ix":3},"x":{"a":0,"k":0,"ix":4},"nm":"Mask 9"},{"inv":false,"mode":"f","pt":{"a":0,"k":{"i":[[0.177,1.905],[0,0],[-1.675,-8.419],[0,0]],"o":[[0,0],[0.8,8.547],[0,0],[-0.366,-1.845]],"v":[[195.017,255.272],[1.088,273.427],[4.803,298.896],[195.834,260.897]],"c":true},"ix":1},"o":{"a":0,"k":100,"ix":3},"x":{"a":0,"k":0,"ix":4},"nm":"Mask 10"},{"inv":false,"mode":"f","pt":{"a":0,"k":{"i":[[-0.191,1.866],[0,0],[0,-8.585],[0,0]],"o":[[0,0],[-0.883,8.54],[0,0],[0,-1.917]],"v":[[195.069,244.448],[1.325,224.421],[0,250.125],[194.78,250.125]],"c":true},"ix":1},"o":{"a":0,"k":100,"ix":3},"x":{"a":0,"k":0,"ix":4},"nm":"Mask 11"},{"inv":false,"mode":"f","pt":{"a":0,"k":{"i":[[0,0],[-0.557,1.799],[0,0],[1.675,-8.42]],"o":[[0.372,-1.873],[0,0],[-2.532,8.204],[0,0]],"v":[[195.834,239.354],[197.23,233.843],[11.117,176.403],[4.803,201.355]],"c":true},"ix":1},"o":{"a":0,"k":100,"ix":3},"x":{"a":0,"k":0,"ix":4},"nm":"Mask 12"},{"inv":false,"mode":"f","pt":{"a":0,"k":{"i":[[0,0],[-0.903,1.658],[0,0],[3.285,-7.932]],"o":[[0.732,-1.757],[0,0],[-4.084,7.552],[0,0]],"v":[[198.984,228.999],[201.438,223.873],[30.089,131.218],[19.029,154.459]],"c":true},"ix":1},"o":{"a":0,"k":100,"ix":3},"x":{"a":0,"k":0,"ix":4},"nm":"Mask 13"},{"inv":false,"mode":"f","pt":{"a":0,"k":{"i":[[0,0],[-1.212,1.453],[0,0],[4.77,-7.138]],"o":[[1.059,-1.574],[0,0],[-5.478,6.61],[0,0]],"v":[[204.109,219.47],[207.518,214.926],[57.513,90.603],[42.131,111.239]],"c":true},"ix":1},"o":{"a":0,"k":100,"ix":3},"x":{"a":0,"k":0,"ix":4},"nm":"Mask 14"},{"inv":false,"mode":"f","pt":{"a":0,"k":{"i":[[0,0],[-1.473,1.191],[0,0],[6.071,-6.071]],"o":[[1.342,-1.334],[0,0],[-6.663,5.414],[0,0]],"v":[[210.994,211.131],[215.219,207.339],[92.332,56.118],[73.219,73.356]],"c":true},"ix":1},"o":{"a":0,"k":100,"ix":3},"x":{"a":0,"k":0,"ix":4},"nm":"Mask 15"},{"inv":false,"mode":"f","pt":{"a":0,"k":{"i":[[0,0],[-1.68,0.882],[0,0],[7.138,-4.77]],"o":[[1.572,-1.045],[0,0],[-7.591,4.011],[0,0]],"v":[[219.365,204.294],[224.246,201.4],[133.21,29.088],[111.102,42.267]],"c":true},"ix":1},"o":{"a":0,"k":100,"ix":3},"x":{"a":0,"k":0,"ix":4},"nm":"Mask 16"},{"inv":false,"mode":"f","pt":{"a":0,"k":{"i":[[0,0],[-1.825,0.536],[0,0],[7.932,-3.285]],"o":[[1.741,-0.715],[0,0],[-8.227,2.453],[0,0]],"v":[[228.905,199.227],[234.256,197.348],[178.576,10.553],[154.321,19.166]],"c":true},"ix":1},"o":{"a":0,"k":100,"ix":3},"x":{"a":0,"k":0,"ix":4},"nm":"Mask 17"},{"inv":false,"mode":"f","pt":{"a":0,"k":{"i":[[0,0],[-0.07,0],[-1.793,-0.176],[0,0],[8.585,0]],"o":[[0.07,0],[1.84,0],[0,0],[-8.54,-0.883],[0,0]],"v":[[250.011,194.878],[250.221,194.877],[255.668,195.144],[275.715,1.211],[250.011,-0.114]],"c":true},"ix":1},"o":{"a":0,"k":100,"ix":3},"x":{"a":0,"k":0,"ix":4},"nm":"Mask 18"},{"inv":false,"mode":"f","pt":{"a":0,"k":{"i":[[-1.797,-0.546],[0,0],[8.422,1.675],[0,0]],"o":[[0,0],[-8.205,-2.532],[0,0],[1.87,0.363]],"v":[[266.253,197.25],[323.735,11.003],[298.781,4.689],[260.751,195.884]],"c":true},"ix":1},"o":{"a":0,"k":100,"ix":3},"x":{"a":0,"k":0,"ix":4},"nm":"Mask 19"},{"inv":false,"mode":"f","pt":{"a":0,"k":{"i":[[0,0],[-1.662,-0.893],[0,0],[7.93,3.285]],"o":[[1.757,0.721],[0,0],[-7.552,-4.083],[0,0]],"v":[[271.095,198.977],[276.225,201.4],[368.918,29.976],[345.679,18.916]],"c":true},"ix":1},"o":{"a":0,"k":100,"ix":3},"x":{"a":0,"k":0,"ix":4},"nm":"Mask 20"},{"inv":false,"mode":"f","pt":{"a":0,"k":{"i":[[-1.457,-1.203],[0,0],[7.137,4.77],[0,0]],"o":[[0,0],[-6.61,-5.478],[0,0],[1.578,1.049]],"v":[[285.192,207.426],[409.534,57.399],[388.897,42.017],[280.635,204.044]],"c":true},"ix":1},"o":{"a":0,"k":100,"ix":3},"x":{"a":0,"k":0,"ix":4},"nm":"Mask 21"},{"inv":false,"mode":"f","pt":{"a":0,"k":{"i":[[-1.2,-1.467],[0,0],[6.07,6.07],[0,0]],"o":[[0,0],[-5.415,-6.663],[0,0],[1.342,1.335]],"v":[[292.822,215.087],[444.02,92.219],[426.781,73.106],[289.007,210.881]],"c":true},"ix":1},"o":{"a":0,"k":100,"ix":3},"x":{"a":0,"k":0,"ix":4},"nm":"Mask 22"},{"inv":false,"mode":"f","pt":{"a":0,"k":{"i":[[-0.892,-1.677],[0,0],[4.77,7.139],[0,0]],"o":[[0,0],[-4.01,-7.591],[0,0],[1.055,1.569]],"v":[[298.814,224.091],[471.049,133.097],[457.869,110.988],[295.892,219.219]],"c":true},"ix":1},"o":{"a":0,"k":100,"ix":3},"x":{"a":0,"k":0,"ix":4},"nm":"Mask 23"},{"inv":false,"mode":"f","pt":{"a":0,"k":{"i":[[-0.545,-1.826],[0,0],[3.285,7.932],[0,0]],"o":[[0,0],[-2.452,-8.228],[0,0],[0.725,1.741]],"v":[[302.924,234.103],[489.583,178.463],[480.971,154.208],[301.016,228.749]],"c":true},"ix":1},"o":{"a":0,"k":100,"ix":3},"x":{"a":0,"k":0,"ix":4},"nm":"Mask 24"},{"inv":false,"mode":"f","pt":{"a":0,"k":{"i":[[-0.175,-1.905],[0,0],[1.675,8.42],[0,0]],"o":[[0,0],[-0.8,-8.547],[0,0],[0.365,1.844]],"v":[[304.981,244.729],[498.912,226.573],[495.198,201.105],[304.166,239.104]],"c":true},"ix":1},"o":{"a":0,"k":100,"ix":3},"x":{"a":0,"k":0,"ix":4},"nm":"Mask 25"},{"inv":false,"mode":"f","pt":{"a":0,"k":{"i":[[0.193,-1.867],[0,0],[0,8.585],[0,0]],"o":[[0,0],[0.883,-8.54],[0,0],[0,1.917]],"v":[[304.929,255.552],[498.675,275.579],[500,249.875],[305.219,249.875]],"c":true},"ix":1},"o":{"a":0,"k":100,"ix":3},"x":{"a":0,"k":0,"ix":4},"nm":"Mask 26"},{"inv":false,"mode":"f","pt":{"a":0,"k":{"i":[[0,0],[0.558,-1.8],[0,0],[-1.675,8.419]],"o":[[-0.37,1.873],[0,0],[2.53,-8.202],[0,0]],"v":[[304.164,260.647],[302.769,266.157],[488.883,323.597],[495.195,298.646]],"c":true},"ix":1},"o":{"a":0,"k":100,"ix":3},"x":{"a":0,"k":0,"ix":4},"nm":"Mask 27"},{"inv":false,"mode":"f","pt":{"a":0,"k":{"i":[[0,0],[0.902,-1.657],[0,0],[-3.285,7.932]],"o":[[-0.733,1.758],[0,0],[4.082,-7.552],[0,0]],"v":[[301.016,271.001],[298.561,276.126],[469.911,368.782],[480.971,345.541]],"c":true},"ix":1},"o":{"a":0,"k":100,"ix":3},"x":{"a":0,"k":0,"ix":4},"nm":"Mask 28"},{"inv":false,"mode":"f","pt":{"a":0,"k":{"i":[[0,0],[1.212,-1.453],[0,0],[-4.77,7.137]],"o":[[-1.057,1.572],[0,0],[5.477,-6.61],[0,0]],"v":[[295.889,280.531],[292.482,285.074],[442.488,409.398],[457.869,388.761]],"c":true},"ix":1},"o":{"a":0,"k":100,"ix":3},"x":{"a":0,"k":0,"ix":4},"nm":"Mask 29"},{"inv":false,"mode":"f","pt":{"a":0,"k":{"i":[[0,0],[1.475,-1.19],[0,0],[-6.072,6.07]],"o":[[-1.34,1.335],[0,0],[6.665,-5.412],[0,0]],"v":[[289.004,288.868],[284.78,292.661],[407.667,443.881],[426.781,426.645]],"c":true},"ix":1},"o":{"a":0,"k":100,"ix":3},"x":{"a":0,"k":0,"ix":4},"nm":"Mask 30"},{"inv":false,"mode":"f","pt":{"a":0,"k":{"i":[[0,0],[1.68,-0.883],[0,0],[-7.14,4.77]],"o":[[-1.572,1.045],[0,0],[7.592,-4.012],[0,0]],"v":[[280.635,295.706],[275.752,298.601],[366.788,470.913],[388.897,457.733]],"c":true},"ix":1},"o":{"a":0,"k":100,"ix":3},"x":{"a":0,"k":0,"ix":4},"nm":"Mask 31"},{"inv":false,"mode":"f","pt":{"a":0,"k":{"i":[[0,0],[1.825,-0.538],[0,0],[-7.93,3.285]],"o":[[-1.742,0.715],[0,0],[8.227,-2.452],[0,0]],"v":[[271.095,300.773],[265.743,302.653],[321.423,489.447],[345.677,480.835]],"c":true},"ix":1},"o":{"a":0,"k":100,"ix":3},"x":{"a":0,"k":0,"ix":4},"nm":"Mask 32"}],"sw":500,"sh":500,"sc":"#000000","ip":0,"op":900.000036657751,"st":0,"bm":0}],"markers":[]}